extract_question_image.py
pydocxextractor-0.1.0.dist-info/METADATA
pydocxextractor-0.1.0.dist-info/WHEEL
pydocxextractor-0.1.0.dist-info/top_level.txt
pydocxextractor-0.1.0.dist-info/RECORD
